hausify/.flake8
hausify/.isort.cfg
hausify/__init__.py
hausify/args.py
hausify/lsp/__init__.py
hausify/lsp/handlers/__init__.py
hausify/lsp/handlers/format_diagnostics_flake8.py
hausify/lsp/handlers/format_diagnostics_mypy.py
hausify/lsp/handlers/handle_did_open_text_document.py
hausify/lsp/handlers/handle_did_save_text_document.py
hausify/lsp/handlers/handle_format_text_document.py
hausify/lsp/handlers/util.py
hausify/lsp/hausify_language_server.py
hausify/main.py
hausify/mypy.ini
hausify/runners/__init__.py
hausify/runners/exec_black.py
hausify/runners/exec_docformatter.py
hausify/runners/exec_flake8.py
hausify/runners/exec_isort.py
hausify/runners/exec_mypy.py
hausify/runners/lsp_exec_black.py
hausify/runners/lsp_exec_docformatter.py
hausify/runners/lsp_exec_flake8.py
hausify/runners/lsp_exec_isort.py
hausify/runners/lsp_exec_mypy.py
hausify/runners/runner.py
hausify/server.py
hausify/timings.py
hausify/util/__init__.py
hausify/util/filesystem.py
hausify/util/python_import_finder.py
hausify/util/python_import_finder_test.py
hausify/util/search.py
hausify/util/search_test.py
hausify/util/testing/__init__.py
hausify/util/testing/build_test_file_structure.py
hausify-0.1.5.dist-info/LICENSE
hausify-0.1.5.dist-info/METADATA
hausify-0.1.5.dist-info/WHEEL
hausify-0.1.5.dist-info/entry_points.txt
hausify-0.1.5.dist-info/RECORD
