Metadata-Version: 2.3
Name: hausify
Version: 0.1.5
Summary: Python linting and formatting tools/configurations
Author: Daniel Walt
Author-email: dan@haus.io
Requires-Python: >=3.9,<4.0
Classifier: Programming Language :: Python :: 3
Classifier: Programming Language :: Python :: 3.9
Classifier: Programming Language :: Python :: 3.10
Classifier: Programming Language :: Python :: 3.11
Classifier: Programming Language :: Python :: 3.12
Classifier: Programming Language :: Python :: 3.13
Requires-Dist: black (>=25.0.0,<26.0.0)
Requires-Dist: docformatter (>=1.7.7,<2.0.0)
Requires-Dist: flake8 (>=7.0.0,<8.0.0)
Requires-Dist: flake8-json (>=24.4.0,<25.0.0)
Requires-Dist: isort (>=6.0.0,<7.0.0)
Requires-Dist: mypy (>=1.0.0,<2.0.0)
Requires-Dist: poetry (>=2.0.0,<3.0.0)
Requires-Dist: pre-commit (>=4.0.0,<5.0.0)
Requires-Dist: pygls (>=1.3.1,<2.0.0)
